{"SURVIVAL":{"offHandItem":{"==":"org.bukkit.inventory.ItemStack","v":1976,"type":"AIR","amount":0},"armorContents":{},"potions":[{"==":"PotionEffect","effect":11,"duration":80,"amplifier":80,"ambient":true,"has-particles":true,"has-icon":true}],"inventoryContents":{"2":{"==":"org.bukkit.inventory.ItemStack","v":1976,"type":"GRASS_BLOCK"},"3":{"==":"org.bukkit.inventory.ItemStack","v":1976,"type":"STONE"},"4":{"==":"org.bukkit.inventory.ItemStack","v":1976,"type":"WOODEN_AXE"},"9":{"==":"org.bukkit.inventory.ItemStack","v":1976,"type":"WOODEN_AXE"}},"enderChestContents":{},"stats":{"ex":"1.1989992","ma":"300","fl":"20","el":"0","xp":"0.0","hp":"20.0","txp":"0","ft":"-20","sa":"4.0","fd":"0.0","ra":"300"}}}