{"stats":{"minecraft:dropped":{"minecraft:drowned_spawn_egg":4,"minecraft:clock":3,"minecraft:blaze_rod":4,"minecraft:book":4,"minecraft:diamond_sword":1,"minecraft:stone":64,"minecraft:diamond_boots":1},"minecraft:custom":{"minecraft:play_one_minute":1780571,"minecraft:leave_game":40,"minecraft:time_since_death":127551,"minecraft:time_since_rest":127594,"minecraft:sprint_one_cm":152226,"minecraft:damage_taken":870,"minecraft:walk_one_cm":205697,"minecraft:drop":18,"minecraft:fly_one_cm":2469849,"minecraft:crouch_one_cm":85,"minecraft:deaths":2,"minecraft:sneak_time":277,"minecraft:walk_under_water_one_cm":2437,"minecraft:jump":763,"minecraft:walk_on_water_one_cm":14,"minecraft:fall_one_cm":10476},"minecraft:picked_up":{"minecraft:oak_sign":2,"minecraft:player_head":3,"minecraft:writable_book":4},"minecraft:mined":{"minecraft:player_head":3},"minecraft:used":{"minecraft:oak_fence":43,"minecraft:dark_oak_stairs":50,"minecraft:petrified_oak_slab":18,"minecraft:mossy_stone_bricks":18,"minecraft:jungle_leaves":6,"minecraft:writable_book":1,"minecraft:iron_bars":40,"minecraft:cobblestone_stairs":33,"minecraft:sandstone_stairs":45,"minecraft:prismarine_brick_slab":22,"minecraft:birch_planks":65,"minecraft:birch_leaves":3,"minecraft:red_sandstone_slab":73,"minecraft:spruce_slab":99,"minecraft:polished_andesite":53,"minecraft:red_nether_bricks":45,"minecraft:oak_planks":25,"minecraft:oak_sign":89,"minecraft:spruce_planks":209,"minecraft:white_terracotta":1,"minecraft:sandstone":37,"minecraft:stone":12,"minecraft:red_mushroom_block":73,"minecraft:red_nether_brick_stairs":35,"minecraft:quartz_stairs":78,"minecraft:grass":16,"minecraft:cobblestone_slab":10,"minecraft:player_head":6,"minecraft:structure_block":2,"minecraft:green_terracotta":2,"minecraft:cracked_stone_bricks":4,"minecraft:torch":14,"minecraft:mossy_cobblestone":4,"minecraft:diamond_block":2,"minecraft:dirt":48,"minecraft:lime_terracotta":9,"minecraft:red_nether_brick_slab":59,"minecraft:yellow_terracotta":14,"minecraft:oak_slab":12,"minecraft:prismarine_bricks":28,"minecraft:prismarine_brick_stairs":17,"minecraft:jungle_planks":57,"minecraft:nether_bricks":3,"minecraft:spruce_stairs":106,"minecraft:birch_sign":4,"minecraft:cobblestone_wall":25,"minecraft:light_gray_terracotta":1,"minecraft:jungle_slab":75,"minecraft:nether_brick_slab":22,"minecraft:oak_wood":20,"minecraft:pink_terracotta":2,"minecraft:chiseled_quartz_block":9,"minecraft:stone_brick_wall":52,"minecraft:spruce_log":65,"minecraft:nether_brick_stairs":12,"minecraft:mushroom_stem":25,"minecraft:red_sandstone_stairs":83,"minecraft:brown_terracotta":367,"minecraft:gray_terracotta":11,"minecraft:stone_brick_slab":10,"minecraft:dark_oak_planks":20,"minecraft:red_sandstone":22,"minecraft:acacia_stairs":25,"minecraft:cyan_terracotta":2,"minecraft:acacia_sign":4,"minecraft:birch_slab":30,"minecraft:dark_oak_log":1,"minecraft:quartz_slab":77,"minecraft:red_wool":73,"minecraft:grass_block":10,"minecraft:oak_stairs":33,"minecraft:barrier":97,"minecraft:slime_block":10,"minecraft:acacia_slab":55,"minecraft:quartz_block":53,"minecraft:jungle_stairs":88,"minecraft:red_terracotta":12,"minecraft:dark_oak_slab":35,"minecraft:smooth_quartz":60,"minecraft:gravel":17,"minecraft:stone_brick_stairs":23,"minecraft:stone_bricks":45,"minecraft:chiseled_stone_bricks":8,"minecraft:diamond_sword":36,"minecraft:cobblestone":115,"minecraft:dark_oak_fence":8,"minecraft:drowned_spawn_egg":10,"minecraft:sandstone_slab":41,"minecraft:andesite":55,"minecraft:gold_block":34,"minecraft:smooth_stone_slab":32,"minecraft:granite_wall":12,"minecraft:coarse_dirt":4,"minecraft:orange_terracotta":16,"minecraft:birch_stairs":51,"minecraft:green_stained_glass":1}},"DataVersion":1976}